<?xml version="1.0" ?>
<tariffStatements xmlns:xsi="http://www.w3.org/2001/XMLSchema-instance" xsi:noNamespaceSchemaLocation="https://raw.githubusercontent.com/Flux-Tailor/rate-plan-schema/refs/tags/v0.99/tariff_statements.xsd">
    <tariffStatement>
        <sourceDocKind>Statement</sourceDocKind>
        <sourceURL>https://ets.dps.ny.gov/ets_web/search/showPDF.cfm?G%3E%29S2%3DJ9JSBW%27%5EJW%2B%20%5CCK4%3FXVAHQQ%3AW%2FLJ%5B%5E%3AICSBNKB%5FC%2A69NBFZ%0A</sourceURL>
        <datePublished>2024-04-15</datePublished>
        <effectivePeriod>
            <startDate>2024-06-01</startDate>
        </effectivePeriod>
        <iedrOrgAbbreviation>CED</iedrOrgAbbreviation>
        <dpsUtilityPscNumber>10</dpsUtilityPscNumber>
        <serviceType>Electric</serviceType>
        <typeCode>ACUF</typeCode>
        <DPSCaseNumber>nan</DPSCaseNumber>
        <generalRuleRefs>https://ets.dps.ny.gov/ets_web/search/searchSubmissionID.cfm?sub_id=2825433</generalRuleRefs>
        <statementCharges>
            <scopeOfApplicability>
                <include>
                    <serviceClasses>
                        <serviceClass>All</serviceClass>
                    </serviceClasses>
                </include>
                <exclude>
                    <serviceClasses>
                        <serviceClass>11</serviceClass>
                    </serviceClasses>
                </exclude>
            </scopeOfApplicability>
            <statementCharge>
                <servicePeriod>
                    <startDate>2024-06-01</startDate>
                </servicePeriod>
                <chargeName>Avg Cost-Trench-Undg</chargeName>
                <description>Avg Cost-Trench-Undg</description>
                <chargeValue>0.0</chargeValue>
                <chargesComponent>delivery</chargesComponent>
            </statementCharge>
        </statementCharges>
    </tariffStatement>
    <tariffStatement>
        <sourceDocKind>Statement</sourceDocKind>
        <sourceURL>https://ets.dps.ny.gov/ets_web/search/showPDF.cfm?G%3E%29S2%3DJ9JSBW%27%5EJO%2F%20LKK4%3FXVAHQQ%3AW%2FLJ%5B%5E%3AICSBNKB%5FC%2A69NBFZ%0A</sourceURL>
        <datePublished>2024-05-24</datePublished>
        <effectivePeriod>
            <startDate>2024-06-01</startDate>
        </effectivePeriod>
        <iedrOrgAbbreviation>CED</iedrOrgAbbreviation>
        <dpsUtilityPscNumber>10</dpsUtilityPscNumber>
        <serviceType>Electric</serviceType>
        <typeCode>AMP</typeCode>
        <DPSCaseNumber>14-M-0565</DPSCaseNumber>
        <generalRuleRefs>https://ets.dps.ny.gov/ets_web/search/searchSubmissionID.cfm?sub_id=2825933</generalRuleRefs>
        <statementCharges>
            <scopeOfApplicability>
                <include>
                    <serviceClasses>
                        <serviceClass>All</serviceClass>
                    </serviceClasses>
                </include>
                <exclude>
                    <serviceClasses>
                        <serviceClass>11</serviceClass>
                    </serviceClasses>
                </exclude>
            </scopeOfApplicability>
            <statementCharge>
                <servicePeriod>
                    <startDate>2024-06-01</startDate>
                </servicePeriod>
                <chargeName>Arrears Mgt. Prog. Surcharge</chargeName>
                <description>Arrears Mgt. Prog. Surcharge</description>
                <chargeValue>0.0013</chargeValue>
                <measurementDefinition>
                    <calculationMethod>by_metered_quantity</calculationMethod>
                    <measurementSource>energy</measurementSource>
                    <unitOfMeasure>Wh</unitOfMeasure>
                    <unitMultiplierPowerOfTen>3</unitMultiplierPowerOfTen>
                    <measurementInterval>
                        <calculationMode>PERIOD</calculationMode>
                        <calcIntervalKind>MONTH</calcIntervalKind>
                        <calcIntervalPer>1</calcIntervalPer>
                    </measurementInterval>
                </measurementDefinition>
                <chargesComponent>delivery</chargesComponent>
            </statementCharge>
        </statementCharges>
    </tariffStatement>
    <tariffStatement>
        <sourceDocKind>Statement</sourceDocKind>
        <sourceURL>https://ets.dps.ny.gov/ets_web/search/showPDF.cfm?G%3E%29S2%3DJ9JSBW%27%5E%3AK%28%21%5CSK4%3FXVAHQQ%3AW%2FLJ%5B%5E%3AICSBNKB%5FC%2A69NBFZ%0A</sourceURL>
        <datePublished>2023-12-15</datePublished>
        <effectivePeriod>
            <startDate>2024-01-01</startDate>
        </effectivePeriod>
        <iedrOrgAbbreviation>CED</iedrOrgAbbreviation>
        <dpsUtilityPscNumber>10</dpsUtilityPscNumber>
        <serviceType>Electric</serviceType>
        <typeCode>CBC</typeCode>
        <DPSCaseNumber>15-E-0751</DPSCaseNumber>
        <generalRuleRefs>https://ets.dps.ny.gov/ets_web/search/searchSubmissionID.cfm?sub_id=2823955</generalRuleRefs>
        <statementCharges>
            <scopeOfApplicability>
                <include>
                    <serviceClasses>
                        <serviceClass>All</serviceClass>
                    </serviceClasses>
                </include>
                <exclude>
                    <serviceClasses>
                        <serviceClass>11</serviceClass>
                    </serviceClasses>
                </exclude>
            </scopeOfApplicability>
            <statementCharge>
                <servicePeriod>
                    <startDate>2024-01-01</startDate>
                </servicePeriod>
                <chargeName>Customer Benefit Contribution</chargeName>
                <description>Customer Benefit Contribution</description>
                <chargeValue>0.0</chargeValue>
                <measurementDefinition>
                    <calculationMethod>by_metered_quantity</calculationMethod>
                    <measurementSource>energy</measurementSource>
                    <unitOfMeasure>W</unitOfMeasure>
                    <unitMultiplierPowerOfTen>3</unitMultiplierPowerOfTen>
                    <measurementInterval>
                        <calculationMode>PERIOD</calculationMode>
                        <calcIntervalKind>MONTH</calcIntervalKind>
                        <calcIntervalPer>1</calcIntervalPer>
                    </measurementInterval>
                </measurementDefinition>
                <chargesComponent>delivery</chargesComponent>
            </statementCharge>
        </statementCharges>
    </tariffStatement>
    <tariffStatement>
        <sourceDocKind>Statement</sourceDocKind>
        <sourceURL>https://ets.dps.ny.gov/ets_web/search/showPDF.cfm?G%3E%29S2%3DJ9JSBW%27%5F%2AO%26%20%5CKK4%3FXVAHQQ%3AW%2FLJ%5B%5E%3AICSBNKB%5FC%2A69NBFZ%0A</sourceURL>
        <datePublished>2022-01-14</datePublished>
        <effectivePeriod>
            <startDate>2022-01-17</startDate>
        </effectivePeriod>
        <iedrOrgAbbreviation>CED</iedrOrgAbbreviation>
        <dpsUtilityPscNumber>10</dpsUtilityPscNumber>
        <serviceType>Electric</serviceType>
        <typeCode>CCA</typeCode>
        <DPSCaseNumber>20-M-0082</DPSCaseNumber>
        <generalRuleRefs>https://ets.dps.ny.gov/ets_web/search/searchSubmissionID.cfm?sub_id=2814995</generalRuleRefs>
        <statementCharges>
            <scopeOfApplicability>
                <include>
                    <serviceClasses>
                        <serviceClass>All</serviceClass>
                    </serviceClasses>
                </include>
                <exclude>
                    <serviceClasses>
                        <serviceClass>11</serviceClass>
                    </serviceClasses>
                </exclude>
            </scopeOfApplicability>
            <statementCharge>
                <servicePeriod>
                    <startDate>2022-01-17</startDate>
                </servicePeriod>
                <chargeName>Community Choice Aggregation</chargeName>
                <description>Community Choice Aggregation</description>
                <chargeValue>0.0</chargeValue>
                <chargesComponent>delivery</chargesComponent>
            </statementCharge>
        </statementCharges>
    </tariffStatement>
    <tariffStatement>
        <sourceDocKind>Statement</sourceDocKind>
        <sourceURL>https://ets.dps.ny.gov/ets_web/search/showPDF.cfm?G%3E%29S2%3DJ9JSBW%27%5E%2AW%2B%21LKK4%3FXVAHQQ%3AW%2FLJ%5B%5E%3AICSBNKB%5FC%2A69NBFZ%0A</sourceURL>
        <datePublished>2023-09-15</datePublished>
        <effectivePeriod>
            <startDate>2023-10-01</startDate>
        </effectivePeriod>
        <iedrOrgAbbreviation>CED</iedrOrgAbbreviation>
        <dpsUtilityPscNumber>10</dpsUtilityPscNumber>
        <serviceType>Electric</serviceType>
        <typeCode>CESD</typeCode>
        <DPSCaseNumber>nan</DPSCaseNumber>
        <generalRuleRefs>https://ets.dps.ny.gov/ets_web/search/searchSubmissionID.cfm?sub_id=2822655</generalRuleRefs>
        <statementCharges>
            <scopeOfApplicability>
                <include>
                    <serviceClasses>
                        <serviceClass>All</serviceClass>
                    </serviceClasses>
                </include>
                <exclude>
                    <serviceClasses>
                        <serviceClass>11</serviceClass>
                    </serviceClasses>
                </exclude>
            </scopeOfApplicability>
            <statementCharge>
                <servicePeriod>
                    <startDate>2023-10-01</startDate>
                </servicePeriod>
                <chargeName>Clean Energy Standard Delivery</chargeName>
                <description>Clean Energy Standard Delivery</description>
                <chargeValue>0.000272</chargeValue>
                <measurementDefinition>
                    <calculationMethod>by_metered_quantity</calculationMethod>
                    <measurementSource>energy</measurementSource>
                    <unitOfMeasure>Wh</unitOfMeasure>
                    <unitMultiplierPowerOfTen>3</unitMultiplierPowerOfTen>
                    <measurementInterval>
                        <calculationMode>PERIOD</calculationMode>
                        <calcIntervalKind>MONTH</calcIntervalKind>
                        <calcIntervalPer>1</calcIntervalPer>
                    </measurementInterval>
                </measurementDefinition>
                <chargesComponent>delivery</chargesComponent>
            </statementCharge>
        </statementCharges>
    </tariffStatement>
    <tariffStatement>
        <sourceDocKind>Statement</sourceDocKind>
        <sourceURL>https://ets.dps.ny.gov/ets_web/search/showPDF.cfm?G%3E%29S2%3DJ9JSBW%27%5EJW%2D%20%3C%5BK4%3FXVAHQQ%3AW%2FLJ%5B%5E%3AICSBNKB%5FC%2A69NBFZ%0A</sourceURL>
        <datePublished>2024-03-29</datePublished>
        <effectivePeriod>
            <startDate>2024-04-01</startDate>
        </effectivePeriod>
        <iedrOrgAbbreviation>CED</iedrOrgAbbreviation>
        <dpsUtilityPscNumber>10</dpsUtilityPscNumber>
        <serviceType>Electric</serviceType>
        <typeCode>CESS</typeCode>
        <DPSCaseNumber>nan</DPSCaseNumber>
        <generalRuleRefs>https://ets.dps.ny.gov/ets_web/search/searchSubmissionID.cfm?sub_id=2825369</generalRuleRefs>
        <statementCharges>
            <scopeOfApplicability>
                <include>
                    <serviceClasses>
                        <serviceClass>All</serviceClass>
                    </serviceClasses>
                </include>
                <exclude>
                    <serviceClasses>
                        <serviceClass>11</serviceClass>
                    </serviceClasses>
                </exclude>
            </scopeOfApplicability>
            <statementCharge>
                <servicePeriod>
                    <startDate>2024-04-01</startDate>
                </servicePeriod>
                <chargeName>Clean Energy Stan. Supply Surc</chargeName>
                <description>Clean Energy Stan. Supply Surc</description>
                <chargeValue>0.007187</chargeValue>
                <measurementDefinition>
                    <calculationMethod>by_metered_quantity</calculationMethod>
                    <measurementSource>energy</measurementSource>
                    <unitOfMeasure>Wh</unitOfMeasure>
                    <unitMultiplierPowerOfTen>3</unitMultiplierPowerOfTen>
                    <measurementInterval>
                        <calculationMode>PERIOD</calculationMode>
                        <calcIntervalKind>MONTH</calcIntervalKind>
                        <calcIntervalPer>1</calcIntervalPer>
                    </measurementInterval>
                </measurementDefinition>
                <chargesComponent>delivery</chargesComponent>
            </statementCharge>
        </statementCharges>
    </tariffStatement>
    <tariffStatement>
        <sourceDocKind>Statement</sourceDocKind>
        <sourceURL>https://ets.dps.ny.gov/ets_web/search/showPDF.cfm?G%3E%29S2%3DJ9JSBW%27%5EJK%28%21%5CSK4%3FXVAHQQ%3AW%2FLJ%5B%5E%3AICSBNKB%5FC%2A69NBFZ%0A</sourceURL>
        <datePublished>2024-05-17</datePublished>
        <effectivePeriod>
            <startDate>2024-06-01</startDate>
        </effectivePeriod>
        <iedrOrgAbbreviation>CED</iedrOrgAbbreviation>
        <dpsUtilityPscNumber>10</dpsUtilityPscNumber>
        <serviceType>Electric</serviceType>
        <typeCode>DLM</typeCode>
        <DPSCaseNumber>15-E-0751</DPSCaseNumber>
        <generalRuleRefs>https://ets.dps.ny.gov/ets_web/search/searchSubmissionID.cfm?sub_id=2825845</generalRuleRefs>
        <statementCharges>
            <scopeOfApplicability>
                <include>
                    <serviceClasses>
                        <serviceClass>All</serviceClass>
                    </serviceClasses>
                </include>
                <exclude>
                    <serviceClasses>
                        <serviceClass>11</serviceClass>
                    </serviceClasses>
                </exclude>
            </scopeOfApplicability>
            <statementCharge>
                <servicePeriod>
                    <startDate>2024-06-01</startDate>
                </servicePeriod>
                <chargeName>Dynamic Load Management Surch</chargeName>
                <description>Dynamic Load Management Surch</description>
                <chargeValue>0.0011</chargeValue>
                <measurementDefinition>
                    <calculationMethod>by_metered_quantity</calculationMethod>
                    <measurementSource>energy</measurementSource>
                    <unitOfMeasure>Wh</unitOfMeasure>
                    <unitMultiplierPowerOfTen>3</unitMultiplierPowerOfTen>
                    <measurementInterval>
                        <calculationMode>PERIOD</calculationMode>
                        <calcIntervalKind>MONTH</calcIntervalKind>
                        <calcIntervalPer>1</calcIntervalPer>
                    </measurementInterval>
                </measurementDefinition>
                <chargesComponent>delivery</chargesComponent>
            </statementCharge>
        </statementCharges>
    </tariffStatement>
    <tariffStatement>
        <sourceDocKind>Statement</sourceDocKind>
        <sourceURL>https://ets.dps.ny.gov/ets_web/search/showPDF.cfm?G%3E%29S2%3DJ9JSBW%20%5EJC%2D%20%5CKK4%3FXVAHQQ%3AW%2FLJ%5B%5E%3AICSBNKB%5FC%2A69NBFZ%0A</sourceURL>
        <datePublished>2020-10-14</datePublished>
        <effectivePeriod>
            <startDate>2020-10-15</startDate>
        </effectivePeriod>
        <iedrOrgAbbreviation>CED</iedrOrgAbbreviation>
        <dpsUtilityPscNumber>10</dpsUtilityPscNumber>
        <serviceType>Electric</serviceType>
        <typeCode>ESCC</typeCode>
        <DPSCaseNumber>nan</DPSCaseNumber>
        <generalRuleRefs>https://ets.dps.ny.gov/ets_web/search/searchSubmissionID.cfm?sub_id=2809323</generalRuleRefs>
        <statementCharges>
            <scopeOfApplicability>
                <include>
                    <serviceClasses>
                        <serviceClass>All</serviceClass>
                    </serviceClasses>
                </include>
                <exclude>
                    <serviceClasses>
                        <serviceClass>11</serviceClass>
                    </serviceClasses>
                </exclude>
            </scopeOfApplicability>
            <statementCharge>
                <servicePeriod>
                    <startDate>2020-10-15</startDate>
                </servicePeriod>
                <chargeName>Emerg. Summer Cooling Credit</chargeName>
                <description>Emerg. Summer Cooling Credit</description>
                <chargeValue>0.0</chargeValue>
                <measurementDefinition>
                    <calculationMethod>by_metered_quantity</calculationMethod>
                    <measurementSource>energy</measurementSource>
                    <unitOfMeasure>Wh</unitOfMeasure>
                    <unitMultiplierPowerOfTen>3</unitMultiplierPowerOfTen>
                    <measurementInterval>
                        <calculationMode>PERIOD</calculationMode>
                        <calcIntervalKind>MONTH</calcIntervalKind>
                        <calcIntervalPer>1</calcIntervalPer>
                    </measurementInterval>
                </measurementDefinition>
                <chargesComponent>delivery</chargesComponent>
            </statementCharge>
        </statementCharges>
    </tariffStatement>
    <tariffStatement>
        <sourceDocKind>Statement</sourceDocKind>
        <sourceURL>https://ets.dps.ny.gov/ets_web/search/showPDF.cfm?G%3E%29S2%3DJ9JSBW%27%5EJK%28%21%5CCK4%3FXVAHQQ%3AW%2FLJ%5B%5E%3AICSBNKB%5FC%2A69NBFZ%0A</sourceURL>
        <datePublished>2024-05-17</datePublished>
        <effectivePeriod>
            <startDate>2024-06-01</startDate>
        </effectivePeriod>
        <iedrOrgAbbreviation>CED</iedrOrgAbbreviation>
        <dpsUtilityPscNumber>10</dpsUtilityPscNumber>
        <serviceType>Electric</serviceType>
        <typeCode>EVS</typeCode>
        <DPSCaseNumber>15-E-0751</DPSCaseNumber>
        <generalRuleRefs>https://ets.dps.ny.gov/ets_web/search/searchSubmissionID.cfm?sub_id=2825845</generalRuleRefs>
        <statementCharges>
            <scopeOfApplicability>
                <include>
                    <serviceClasses>
                        <serviceClass>All</serviceClass>
                    </serviceClasses>
                </include>
                <exclude>
                    <serviceClasses>
                        <serviceClass>11</serviceClass>
                    </serviceClasses>
                </exclude>
            </scopeOfApplicability>
            <statementCharge>
                <servicePeriod>
                    <startDate>2024-06-01</startDate>
                </servicePeriod>
                <chargeName>Electric Vehicle Statement</chargeName>
                <description>Electric Vehicle Statement</description>
                <chargeValue>0.0002</chargeValue>
                <measurementDefinition>
                    <calculationMethod>by_metered_quantity</calculationMethod>
                    <measurementSource>energy</measurementSource>
                    <unitOfMeasure>Wh</unitOfMeasure>
                    <unitMultiplierPowerOfTen>3</unitMultiplierPowerOfTen>
                    <measurementInterval>
                        <calculationMode>PERIOD</calculationMode>
                        <calcIntervalKind>MONTH</calcIntervalKind>
                        <calcIntervalPer>1</calcIntervalPer>
                    </measurementInterval>
                </measurementDefinition>
                <chargesComponent>delivery</chargesComponent>
            </statementCharge>
        </statementCharges>
    </tariffStatement>
    <tariffStatement>
        <sourceDocKind>Statement</sourceDocKind>
        <sourceURL>https://ets.dps.ny.gov/ets_web/search/showPDF.cfm?G%3E%29S2%3DJ9JSBW%27%5EJK%29%20%2C%5BK4%3FXVAHQQ%3AW%2FLJ%5B%5E%3AICSBNKB%5FC%2A69NBFZ%0A</sourceURL>
        <datePublished>2024-05-15</datePublished>
        <effectivePeriod>
            <startDate>2024-05-31</startDate>
        </effectivePeriod>
        <iedrOrgAbbreviation>CED</iedrOrgAbbreviation>
        <dpsUtilityPscNumber>10</dpsUtilityPscNumber>
        <serviceType>Electric</serviceType>
        <typeCode>GRT</typeCode>
        <DPSCaseNumber>nan</DPSCaseNumber>
        <generalRuleRefs>https://ets.dps.ny.gov/ets_web/search/searchSubmissionID.cfm?sub_id=2825805</generalRuleRefs>
        <statementCharges>
            <scopeOfApplicability>
                <include>
                    <serviceClasses>
                        <serviceClass>All</serviceClass>
                    </serviceClasses>
                </include>
                <exclude>
                    <serviceClasses>
                        <serviceClass>11</serviceClass>
                    </serviceClasses>
                </exclude>
            </scopeOfApplicability>
            <statementCharge>
                <servicePeriod>
                    <startDate>2024-05-31</startDate>
                </servicePeriod>
                <chargeName>Revenue Tax Surcharge</chargeName>
                <description>Revenue Tax Surcharge</description>
                <chargeValue>0.022195</chargeValue>
                <measurementDefinition>
                    <calculationMethod>percentage</calculationMethod>
                    <measurementSource>energy</measurementSource>
                    <unitOfMeasure>Wh</unitOfMeasure>
                    <unitMultiplierPowerOfTen>1</unitMultiplierPowerOfTen>
                    <measurementInterval>
                        <calculationMode>PERIOD</calculationMode>
                        <calcIntervalKind>MONTH</calcIntervalKind>
                        <calcIntervalPer>1</calcIntervalPer>
                    </measurementInterval>
                </measurementDefinition>
                <chargesComponent>delivery</chargesComponent>
            </statementCharge>
        </statementCharges>
    </tariffStatement>
    <tariffStatement>
        <sourceDocKind>Statement</sourceDocKind>
        <sourceURL>https://ets.dps.ny.gov/ets_web/search/showPDF.cfm?G%3E%29S2%3DJ9JSBW%27%5EJK%29%20%2C%5BK4%3FXVAHQQ%3AW%2FLJ%5B%5E%3AICSBNKB%5FC%2A69NBFZ%0A</sourceURL>
        <datePublished>2024-05-15</datePublished>
        <effectivePeriod>
            <startDate>2024-05-31</startDate>
        </effectivePeriod>
        <iedrOrgAbbreviation>CED</iedrOrgAbbreviation>
        <dpsUtilityPscNumber>10</dpsUtilityPscNumber>
        <serviceType>Electric</serviceType>
        <typeCode>GRT</typeCode>
        <DPSCaseNumber>nan</DPSCaseNumber>
        <generalRuleRefs>https://ets.dps.ny.gov/ets_web/search/searchSubmissionID.cfm?sub_id=2825805</generalRuleRefs>
        <statementCharges>
            <scopeOfApplicability>
                <include>
                    <serviceClasses>
                        <serviceClass>All</serviceClass>
                    </serviceClasses>
                </include>
                <exclude>
                    <serviceClasses>
                        <serviceClass>11</serviceClass>
                    </serviceClasses>
                </exclude>
            </scopeOfApplicability>
            <statementCharge>
                <servicePeriod>
                    <startDate>2024-05-31</startDate>
                </servicePeriod>
                <chargeName>Revenue Tax Surcharge</chargeName>
                <description>Revenue Tax Surcharge</description>
                <chargeValue>0.024066</chargeValue>
                <measurementDefinition>
                    <calculationMethod>percentage</calculationMethod>
                    <measurementSource>energy</measurementSource>
                    <unitOfMeasure>Wh</unitOfMeasure>
                    <unitMultiplierPowerOfTen>1</unitMultiplierPowerOfTen>
                    <measurementInterval>
                        <calculationMode>PERIOD</calculationMode>
                        <calcIntervalKind>MONTH</calcIntervalKind>
                        <calcIntervalPer>1</calcIntervalPer>
                    </measurementInterval>
                </measurementDefinition>
                <chargesComponent>supply</chargesComponent>
            </statementCharge>
        </statementCharges>
    </tariffStatement>
    <tariffStatement>
        <sourceDocKind>Statement</sourceDocKind>
        <sourceURL>https://ets.dps.ny.gov/ets_web/search/showPDF.cfm?G%3E%29S2%3DJ9JSBW%23%5FJ%3B%26%21LCK4%3FXVAHQQ%3AW%2FLJ%5B%5E%3AICSBNKB%5FC%2A69NBFZ%0A</sourceURL>
        <datePublished>2013-10-03</datePublished>
        <effectivePeriod>
            <startDate>2013-11-01</startDate>
        </effectivePeriod>
        <iedrOrgAbbreviation>CED</iedrOrgAbbreviation>
        <dpsUtilityPscNumber>10</dpsUtilityPscNumber>
        <serviceType>Electric</serviceType>
        <typeCode>ICAP</typeCode>
        <DPSCaseNumber>nan</DPSCaseNumber>
        <generalRuleRefs>https://ets.dps.ny.gov/ets_web/search/searchSubmissionID.cfm?sub_id=2774085</generalRuleRefs>
        <statementCharges>
            <scopeOfApplicability>
                <include>
                    <serviceClasses>
                        <serviceClass>All</serviceClass>
                    </serviceClasses>
                </include>
                <exclude>
                    <serviceClasses>
                        <serviceClass>11</serviceClass>
                    </serviceClasses>
                </exclude>
            </scopeOfApplicability>
            <statementCharge>
                <servicePeriod>
                    <startDate>2013-11-01</startDate>
                </servicePeriod>
                <chargeName>Installed Capacity Payment</chargeName>
                <description>Installed Capacity Payment</description>
                <chargeValue>7.54</chargeValue>
                <measurementDefinition>
                    <calculationMethod>by_metered_quantity</calculationMethod>
                    <measurementSource>energy</measurementSource>
                    <unitOfMeasure>W</unitOfMeasure>
                    <unitMultiplierPowerOfTen>3</unitMultiplierPowerOfTen>
                    <measurementInterval>
                        <calculationMode>PERIOD</calculationMode>
                        <calcIntervalKind>MONTH</calcIntervalKind>
                        <calcIntervalPer>1</calcIntervalPer>
                    </measurementInterval>
                </measurementDefinition>
                <chargesComponent>delivery</chargesComponent>
            </statementCharge>
        </statementCharges>
    </tariffStatement>
    <tariffStatement>
        <sourceDocKind>Statement</sourceDocKind>
        <sourceURL>https://ets.dps.ny.gov/ets_web/search/showPDF.cfm?G%3E%29S2%3DJ9JSBW%27%5E%2A%3B%2C%21%3CCK4%3FXVAHQQ%3AW%2FLJ%5B%5E%3AICSBNKB%5FC%2A69NBFZ%0A</sourceURL>
        <datePublished>2023-11-01</datePublished>
        <effectivePeriod>
            <startDate>2023-12-01</startDate>
        </effectivePeriod>
        <iedrOrgAbbreviation>CED</iedrOrgAbbreviation>
        <dpsUtilityPscNumber>10</dpsUtilityPscNumber>
        <serviceType>Electric</serviceType>
        <typeCode>LIC</typeCode>
        <DPSCaseNumber>14-M-0565</DPSCaseNumber>
        <generalRuleRefs>https://ets.dps.ny.gov/ets_web/search/searchSubmissionID.cfm?sub_id=2823331</generalRuleRefs>
        <statementCharges>
            <scopeOfApplicability>
                <include>
                    <serviceClasses>
                        <serviceClass>All</serviceClass>
                    </serviceClasses>
                </include>
                <exclude>
                    <serviceClasses>
                        <serviceClass>10</serviceClass>
                        <serviceClass>11</serviceClass>
                    </serviceClasses>
                </exclude>
            </scopeOfApplicability>
            <statementCharge>
                <servicePeriod>
                    <startDate>2023-12-01</startDate>
                </servicePeriod>
                <chargeName>LICAAP Discounts</chargeName>
                <description>Low Income Customer Affordability Assistance Program (LICAAP) Discounts</description>
                <chargeValue>0.0</chargeValue>
                <chargesComponent>delivery</chargesComponent>
            </statementCharge>
        </statementCharges>
    </tariffStatement>
    <tariffStatement>
        <sourceDocKind>Statement</sourceDocKind>
        <sourceURL>https://ets.dps.ny.gov/ets_web/search/showPDF.cfm?G%3E%29S2%3DJ9JSBW%27%5EJO%27%20%5C%23K4%3FXVAHQQ%3AW%2FLJ%5B%5E%3AICSBNKB%5FC%2A69NBFZ%0A</sourceURL>
        <datePublished>2024-05-29</datePublished>
        <effectivePeriod>
            <startDate>2024-06-01</startDate>
        </effectivePeriod>
        <iedrOrgAbbreviation>CED</iedrOrgAbbreviation>
        <dpsUtilityPscNumber>10</dpsUtilityPscNumber>
        <serviceType>Electric</serviceType>
        <typeCode>MAC</typeCode>
        <DPSCaseNumber>nan</DPSCaseNumber>
        <generalRuleRefs>https://ets.dps.ny.gov/ets_web/search/searchSubmissionID.cfm?sub_id=2825995</generalRuleRefs>
        <statementCharges>
            <scopeOfApplicability>
                <include>
                    <serviceClasses>
                        <serviceClass>All</serviceClass>
                    </serviceClasses>
                </include>
                <exclude>
                    <serviceClasses>
                        <serviceClass>11</serviceClass>
                    </serviceClasses>
                </exclude>
            </scopeOfApplicability>
            <statementCharge>
                <servicePeriod>
                    <startDate>2024-06-01</startDate>
                </servicePeriod>
                <chargeName>Monthly Adjustment Clause</chargeName>
                <description>Monthly Adjustment Clause</description>
                <chargeValue>0.00859</chargeValue>
                <measurementDefinition>
                    <calculationMethod>by_metered_quantity</calculationMethod>
                    <measurementSource>energy</measurementSource>
                    <unitOfMeasure>Wh</unitOfMeasure>
                    <unitMultiplierPowerOfTen>3</unitMultiplierPowerOfTen>
                    <measurementInterval>
                        <calculationMode>PERIOD</calculationMode>
                        <calcIntervalKind>MONTH</calcIntervalKind>
                        <calcIntervalPer>1</calcIntervalPer>
                    </measurementInterval>
                </measurementDefinition>
                <chargesComponent>delivery</chargesComponent>
            </statementCharge>
        </statementCharges>
    </tariffStatement>
    <tariffStatement>
        <sourceDocKind>Statement</sourceDocKind>
        <sourceURL>https://ets.dps.ny.gov/ets_web/search/showPDF.cfm?G%3E%29S2%3DJ9JSBW%27%5EJK%2B%22%5CKK4%3FXVAHQQ%3AW%2FLJ%5B%5E%3AICSBNKB%5FC%2A69NBFZ%0A</sourceURL>
        <datePublished>2024-05-07</datePublished>
        <effectivePeriod>
            <startDate>2024-05-10</startDate>
        </effectivePeriod>
        <iedrOrgAbbreviation>CED</iedrOrgAbbreviation>
        <dpsUtilityPscNumber>10</dpsUtilityPscNumber>
        <serviceType>Electric</serviceType>
        <typeCode>MAC ADJ</typeCode>
        <DPSCaseNumber>nan</DPSCaseNumber>
        <generalRuleRefs>https://ets.dps.ny.gov/ets_web/search/searchSubmissionID.cfm?sub_id=2825771</generalRuleRefs>
        <statementCharges>
            <scopeOfApplicability>
                <include>
                    <serviceClasses>
                        <serviceClass>All</serviceClass>
                    </serviceClasses>
                </include>
                <exclude>
                    <serviceClasses>
                        <serviceClass>11</serviceClass>
                    </serviceClasses>
                </exclude>
            </scopeOfApplicability>
            <statementCharge>
                <servicePeriod>
                    <startDate>2024-05-10</startDate>
                </servicePeriod>
                <chargeName>Monthly Adjustment Clause Adj</chargeName>
                <description>Monthly Adjustment Clause Adj</description>
                <chargeValue>0.00154</chargeValue>
                <measurementDefinition>
                    <calculationMethod>by_metered_quantity</calculationMethod>
                    <measurementSource>energy</measurementSource>
                    <unitOfMeasure>Wh</unitOfMeasure>
                    <unitMultiplierPowerOfTen>3</unitMultiplierPowerOfTen>
                    <measurementInterval>
                        <calculationMode>PERIOD</calculationMode>
                        <calcIntervalKind>MONTH</calcIntervalKind>
                        <calcIntervalPer>1</calcIntervalPer>
                    </measurementInterval>
                </measurementDefinition>
                <chargesComponent>delivery</chargesComponent>
            </statementCharge>
        </statementCharges>
    </tariffStatement>
    <tariffStatement>
        <sourceDocKind>Statement</sourceDocKind>
        <sourceURL>https://ets.dps.ny.gov/ets_web/search/showPDF.cfm?G%3E%29S2%3DJ9JSBW%27%5EJ%5B%2D%21%5CSK4%3FXVAHQQ%3AW%2FLJ%5B%5E%3AICSBNKB%5FC%2A69NBFZ%0A</sourceURL>
        <datePublished>2024-02-01</datePublished>
        <effectivePeriod>
            <startDate>2024-02-02</startDate>
        </effectivePeriod>
        <iedrOrgAbbreviation>CED</iedrOrgAbbreviation>
        <dpsUtilityPscNumber>10</dpsUtilityPscNumber>
        <serviceType>Electric</serviceType>
        <typeCode>MCPI</typeCode>
        <DPSCaseNumber>22-E-0236</DPSCaseNumber>
        <generalRuleRefs>https://ets.dps.ny.gov/ets_web/search/searchSubmissionID.cfm?sub_id=2824685</generalRuleRefs>
        <statementCharges>
            <scopeOfApplicability>
                <include>
                    <serviceClasses>
                        <serviceClass>All</serviceClass>
                    </serviceClasses>
                </include>
                <exclude>
                    <serviceClasses>
                        <serviceClass>11</serviceClass>
                    </serviceClasses>
                </exclude>
            </scopeOfApplicability>
            <statementCharge>
                <servicePeriod>
                    <startDate>2024-02-02</startDate>
                </servicePeriod>
                <chargeName>Managed Charging Participation</chargeName>
                <description>Managed Charging Participation</description>
                <chargeValue>0.0</chargeValue>
                <chargesComponent>delivery</chargesComponent>
            </statementCharge>
        </statementCharges>
    </tariffStatement>
    <tariffStatement>
        <sourceDocKind>Statement</sourceDocKind>
        <sourceURL>https://ets.dps.ny.gov/ets_web/search/showPDF.cfm?G%3E%29S2%3DJ9JSBW%27%5EJO%27%20LSK4%3FXVAHQQ%3AW%2FLJ%5B%5E%3AICSBNKB%5FC%2A69NBFZ%0A</sourceURL>
        <datePublished>2024-05-29</datePublished>
        <effectivePeriod>
            <startDate>2024-06-01</startDate>
        </effectivePeriod>
        <iedrOrgAbbreviation>CED</iedrOrgAbbreviation>
        <dpsUtilityPscNumber>10</dpsUtilityPscNumber>
        <serviceType>Electric</serviceType>
        <typeCode>MFC</typeCode>
        <DPSCaseNumber>nan</DPSCaseNumber>
        <generalRuleRefs>https://ets.dps.ny.gov/ets_web/search/searchSubmissionID.cfm?sub_id=2825991</generalRuleRefs>
        <statementCharges>
            <scopeOfApplicability>
                <include>
                    <serviceClasses>
                        <serviceClass>All</serviceClass>
                    </serviceClasses>
                </include>
                <exclude>
                    <serviceClasses>
                        <serviceClass>11</serviceClass>
                    </serviceClasses>
                </exclude>
            </scopeOfApplicability>
            <statementCharge>
                <servicePeriod>
                    <startDate>2024-06-01</startDate>
                </servicePeriod>
                <chargeName>Merchant Function Charge</chargeName>
                <description>Merchant Function Charge</description>
                <chargeValue>0.113484</chargeValue>
                <measurementDefinition>
                    <calculationMethod>by_metered_quantity</calculationMethod>
                    <measurementSource>energy</measurementSource>
                    <unitOfMeasure>Wh</unitOfMeasure>
                    <unitMultiplierPowerOfTen>3</unitMultiplierPowerOfTen>
                    <measurementInterval>
                        <calculationMode>PERIOD</calculationMode>
                        <calcIntervalKind>MONTH</calcIntervalKind>
                        <calcIntervalPer>1</calcIntervalPer>
                    </measurementInterval>
                </measurementDefinition>
                <chargesComponent>supply</chargesComponent>
            </statementCharge>
        </statementCharges>
    </tariffStatement>
    <tariffStatement>
        <sourceDocKind>Statement</sourceDocKind>
        <sourceURL>https://ets.dps.ny.gov/ets_web/search/showPDF.cfm?G%3E%29S2%3DJ9JSBW%27%5EJK%2B%22%5CSK4%3FXVAHQQ%3AW%2FLJ%5B%5E%3AICSBNKB%5FC%2A69NBFZ%0A</sourceURL>
        <datePublished>2024-05-07</datePublished>
        <effectivePeriod>
            <startDate>2024-05-10</startDate>
        </effectivePeriod>
        <iedrOrgAbbreviation>CED</iedrOrgAbbreviation>
        <dpsUtilityPscNumber>10</dpsUtilityPscNumber>
        <serviceType>Electric</serviceType>
        <typeCode>MSC ADJ</typeCode>
        <DPSCaseNumber>nan</DPSCaseNumber>
        <generalRuleRefs>https://ets.dps.ny.gov/ets_web/search/searchSubmissionID.cfm?sub_id=2825771</generalRuleRefs>
        <statementCharges>
            <scopeOfApplicability>
                <include>
                    <serviceClasses>
                        <serviceClass>All</serviceClass>
                    </serviceClasses>
                </include>
                <exclude>
                    <serviceClasses>
                        <serviceClass>11</serviceClass>
                    </serviceClasses>
                </exclude>
            </scopeOfApplicability>
            <statementCharge>
                <servicePeriod>
                    <startDate>2024-05-10</startDate>
                </servicePeriod>
                <chargeName>Monthly Supply Charge Adjustme</chargeName>
                <description>Monthly Supply Charge Adjustme</description>
                <chargeValue>-0.008014</chargeValue>
                <measurementDefinition>
                    <calculationMethod>by_metered_quantity</calculationMethod>
                    <measurementSource>energy</measurementSource>
                    <unitOfMeasure>Wh</unitOfMeasure>
                    <unitMultiplierPowerOfTen>3</unitMultiplierPowerOfTen>
                    <measurementInterval>
                        <calculationMode>PERIOD</calculationMode>
                        <calcIntervalKind>MONTH</calcIntervalKind>
                        <calcIntervalPer>1</calcIntervalPer>
                    </measurementInterval>
                </measurementDefinition>
                <chargesComponent>supply</chargesComponent>
            </statementCharge>
        </statementCharges>
    </tariffStatement>
    <tariffStatement>
        <sourceDocKind>Statement</sourceDocKind>
        <sourceURL>https://ets.dps.ny.gov/ets_web/search/showPDF.cfm?G%3E%29S2%3DJ9JSBW%27%5EJO%28%22%5CKK4%3FXVAHQQ%3AW%2FLJ%5B%5E%3AICSBNKB%5FC%2A69NBFZ%0A</sourceURL>
        <datePublished>2024-05-29</datePublished>
        <effectivePeriod>
            <startDate>2024-06-01</startDate>
        </effectivePeriod>
        <iedrOrgAbbreviation>CED</iedrOrgAbbreviation>
        <dpsUtilityPscNumber>10</dpsUtilityPscNumber>
        <serviceType>Electric</serviceType>
        <typeCode>MSC CAP</typeCode>
        <DPSCaseNumber>nan</DPSCaseNumber>
        <generalRuleRefs>https://ets.dps.ny.gov/ets_web/search/searchSubmissionID.cfm?sub_id=2825985</generalRuleRefs>
        <statementCharges>
            <scopeOfApplicability>
                <include>
                    <serviceClasses>
                        <serviceClass>All</serviceClass>
                    </serviceClasses>
                </include>
                <exclude>
                    <serviceClasses>
                        <serviceClass>11</serviceClass>
                    </serviceClasses>
                </exclude>
            </scopeOfApplicability>
            <statementCharge>
                <servicePeriod>
                    <startDate>2024-06-01</startDate>
                </servicePeriod>
                <chargeName>Market Supply Charge-Capacity</chargeName>
                <description>Market Supply Charge-Capacity</description>
                <chargeValue>0.0394</chargeValue>
                <measurementDefinition>
                    <calculationMethod>by_metered_quantity</calculationMethod>
                    <measurementSource>energy</measurementSource>
                    <unitOfMeasure>Wh</unitOfMeasure>
                    <unitMultiplierPowerOfTen>3</unitMultiplierPowerOfTen>
                    <measurementInterval>
                        <calculationMode>PERIOD</calculationMode>
                        <calcIntervalKind>MONTH</calcIntervalKind>
                        <calcIntervalPer>1</calcIntervalPer>
                    </measurementInterval>
                </measurementDefinition>
                <chargesComponent>supply</chargesComponent>
            </statementCharge>
        </statementCharges>
    </tariffStatement>
    <tariffStatement>
        <sourceDocKind>Statement</sourceDocKind>
        <sourceURL>https://ets.dps.ny.gov/ets_web/search/showPDF.cfm?G%3E%29S2%3DJ9JSBW%27%5E%3A%3F%2E%21%3CKK4%3FXVAHQQ%3AW%2FLJ%5B%5E%3AICSBNKB%5FC%2A69NBFZ%0A</sourceURL>
        <datePublished>2024-01-29</datePublished>
        <effectivePeriod>
            <startDate>2024-02-01</startDate>
        </effectivePeriod>
        <iedrOrgAbbreviation>CED</iedrOrgAbbreviation>
        <dpsUtilityPscNumber>10</dpsUtilityPscNumber>
        <serviceType>Electric</serviceType>
        <typeCode>RDM</typeCode>
        <DPSCaseNumber>nan</DPSCaseNumber>
        <generalRuleRefs>https://ets.dps.ny.gov/ets_web/search/searchSubmissionID.cfm?sub_id=2824561</generalRuleRefs>
        <statementCharges>
            <scopeOfApplicability>
                <include>
                    <serviceClasses>
                        <serviceClass>All</serviceClass>
                    </serviceClasses>
                </include>
                <exclude>
                    <serviceClasses>
                        <serviceClass>10</serviceClass>
                        <serviceClass>11</serviceClass>
                    </serviceClasses>
                </exclude>
            </scopeOfApplicability>
            <statementCharge>
                <servicePeriod>
                    <startDate>2024-02-01</startDate>
                </servicePeriod>
                <chargeName>Revenue Decoupling Mechanism</chargeName>
                <description>Revenue Decoupling Mechanism</description>
                <chargeValue>-0.0031</chargeValue>
                <measurementDefinition>
                    <calculationMethod>by_metered_quantity</calculationMethod>
                    <measurementSource>energy</measurementSource>
                    <unitOfMeasure>Wh</unitOfMeasure>
                    <unitMultiplierPowerOfTen>3</unitMultiplierPowerOfTen>
                    <measurementInterval>
                        <calculationMode>PERIOD</calculationMode>
                        <calcIntervalKind>MONTH</calcIntervalKind>
                        <calcIntervalPer>1</calcIntervalPer>
                    </measurementInterval>
                </measurementDefinition>
                <chargesComponent>delivery</chargesComponent>
            </statementCharge>
        </statementCharges>
    </tariffStatement>
    <tariffStatement>
        <sourceDocKind>Statement</sourceDocKind>
        <sourceURL>https://ets.dps.ny.gov/ets_web/search/showPDF.cfm?G%3E%29S2%3DJ9JSBW%27%5E%3AK%2A%20LKK4%3FXVAHQQ%3AW%2FLJ%5B%5E%3AICSBNKB%5FC%2A69NBFZ%0A</sourceURL>
        <datePublished>2023-12-15</datePublished>
        <effectivePeriod>
            <startDate>2024-01-01</startDate>
        </effectivePeriod>
        <iedrOrgAbbreviation>CED</iedrOrgAbbreviation>
        <dpsUtilityPscNumber>10</dpsUtilityPscNumber>
        <serviceType>Electric</serviceType>
        <typeCode>SBC</typeCode>
        <DPSCaseNumber>nan</DPSCaseNumber>
        <generalRuleRefs>https://ets.dps.ny.gov/ets_web/search/searchSubmissionID.cfm?sub_id=2823939</generalRuleRefs>
        <statementCharges>
            <scopeOfApplicability>
                <include>
                    <serviceClasses>
                        <serviceClass>All</serviceClass>
                    </serviceClasses>
                </include>
                <exclude>
                    <serviceClasses>
                        <serviceClass>11</serviceClass>
                    </serviceClasses>
                </exclude>
            </scopeOfApplicability>
            <statementCharge>
                <servicePeriod>
                    <startDate>2024-01-01</startDate>
                </servicePeriod>
                <chargeName>System Benefits Charge</chargeName>
                <description>System Benefits Charge</description>
                <chargeValue>0.0065</chargeValue>
                <measurementDefinition>
                    <calculationMethod>by_metered_quantity</calculationMethod>
                    <measurementSource>energy</measurementSource>
                    <unitOfMeasure>Wh</unitOfMeasure>
                    <unitMultiplierPowerOfTen>3</unitMultiplierPowerOfTen>
                    <measurementInterval>
                        <calculationMode>PERIOD</calculationMode>
                        <calcIntervalKind>MONTH</calcIntervalKind>
                        <calcIntervalPer>1</calcIntervalPer>
                    </measurementInterval>
                </measurementDefinition>
                <chargesComponent>delivery</chargesComponent>
            </statementCharge>
        </statementCharges>
    </tariffStatement>
    <tariffStatement>
        <sourceDocKind>Statement</sourceDocKind>
        <sourceURL>https://ets.dps.ny.gov/ets_web/search/showPDF.cfm?G%3E%29S2%3DJ9JSBW%27%5EJK%28%21%5C%5BK4%3FXVAHQQ%3AW%2FLJ%5B%5E%3AICSBNKB%5FC%2A69NBFZ%0A</sourceURL>
        <datePublished>2024-05-17</datePublished>
        <effectivePeriod>
            <startDate>2024-06-01</startDate>
        </effectivePeriod>
        <iedrOrgAbbreviation>CED</iedrOrgAbbreviation>
        <dpsUtilityPscNumber>10</dpsUtilityPscNumber>
        <serviceType>Electric</serviceType>
        <typeCode>SDR</typeCode>
        <DPSCaseNumber>15-E-0751</DPSCaseNumber>
        <generalRuleRefs>https://ets.dps.ny.gov/ets_web/search/searchSubmissionID.cfm?sub_id=2825845</generalRuleRefs>
        <statementCharges>
            <scopeOfApplicability>
                <include>
                    <serviceClasses>
                        <serviceClass>All</serviceClass>
                    </serviceClasses>
                </include>
                <exclude>
                    <serviceClasses>
                        <serviceClass>11</serviceClass>
                    </serviceClasses>
                </exclude>
            </scopeOfApplicability>
            <statementCharge>
                <servicePeriod>
                    <startDate>2024-06-01</startDate>
                </servicePeriod>
                <chargeName>Delivery Revenue Surcharge</chargeName>
                <description>Delivery Revenue Surcharge</description>
                <chargeValue>0.007578</chargeValue>
                <chargesComponent>delivery</chargesComponent>
            </statementCharge>
        </statementCharges>
    </tariffStatement>
    <tariffStatement>
        <sourceDocKind>Statement</sourceDocKind>
        <sourceURL>https://ets.dps.ny.gov/ets_web/search/showPDF.cfm?G%3E%29S2%3DJ9JSBW%20%5FZG%2A%20%2C%5BK4%3FXVAHQQ%3AW%2FLJ%5B%5E%3AICSBNKB%5FC%2A69NBFZ%0A</sourceURL>
        <datePublished>2019-12-23</datePublished>
        <effectivePeriod>
            <startDate>2020-01-01</startDate>
        </effectivePeriod>
        <iedrOrgAbbreviation>CED</iedrOrgAbbreviation>
        <dpsUtilityPscNumber>10</dpsUtilityPscNumber>
        <serviceType>Electric</serviceType>
        <typeCode>TAX</typeCode>
        <DPSCaseNumber>17-M-0815</DPSCaseNumber>
        <generalRuleRefs>https://ets.dps.ny.gov/ets_web/search/searchSubmissionID.cfm?sub_id=2805571</generalRuleRefs>
        <statementCharges>
            <scopeOfApplicability>
                <include>
                    <serviceClasses>
                        <serviceClass>All</serviceClass>
                    </serviceClasses>
                </include>
                <exclude>
                    <serviceClasses>
                        <serviceClass>11</serviceClass>
                    </serviceClasses>
                </exclude>
            </scopeOfApplicability>
            <statementCharge>
                <servicePeriod>
                    <startDate>2020-01-01</startDate>
                </servicePeriod>
                <chargeName>Tax Statement</chargeName>
                <description>Tax Statement</description>
                <chargeValue>0.0</chargeValue>
                <measurementDefinition>
                    <calculationMethod>by_metered_quantity</calculationMethod>
                    <measurementSource>energy</measurementSource>
                    <unitOfMeasure>Wh</unitOfMeasure>
                    <unitMultiplierPowerOfTen>1</unitMultiplierPowerOfTen>
                    <measurementInterval>
                        <calculationMode>PERIOD</calculationMode>
                        <calcIntervalKind>MONTH</calcIntervalKind>
                        <calcIntervalPer>1</calcIntervalPer>
                    </measurementInterval>
                </measurementDefinition>
                <chargesComponent>bundled</chargesComponent>
            </statementCharge>
        </statementCharges>
    </tariffStatement>
    <tariffStatement>
        <sourceDocKind>Statement</sourceDocKind>
        <sourceURL>https://ets.dps.ny.gov/ets_web/search/showPDF.cfm?G%3E%29S2%3DJ9JSBW%27%5E%2AS%2E%21%2C%23K4%3FXVAHQQ%3AW%2FLJ%5B%5E%3AICSBNKB%5FC%2A69NBFZ%0A</sourceURL>
        <datePublished>2023-08-01</datePublished>
        <effectivePeriod>
            <startDate>2023-09-01</startDate>
        </effectivePeriod>
        <iedrOrgAbbreviation>CED</iedrOrgAbbreviation>
        <dpsUtilityPscNumber>10</dpsUtilityPscNumber>
        <serviceType>Electric</serviceType>
        <typeCode>TEL</typeCode>
        <DPSCaseNumber>nan</DPSCaseNumber>
        <generalRuleRefs>https://ets.dps.ny.gov/ets_web/search/searchSubmissionID.cfm?sub_id=2822235</generalRuleRefs>
        <statementCharges>
            <scopeOfApplicability>
                <include>
                    <serviceClasses>
                        <serviceClass>All</serviceClass>
                    </serviceClasses>
                </include>
                <exclude>
                    <serviceClasses>
                        <serviceClass>11</serviceClass>
                    </serviceClasses>
                </exclude>
            </scopeOfApplicability>
            <statementCharge>
                <servicePeriod>
                    <startDate>2023-09-01</startDate>
                </servicePeriod>
                <chargeName>Price Listed Rates and Charges</chargeName>
                <description>Price Listed Rates and Charges</description>
                <chargeValue>0.0</chargeValue>
                <chargesComponent>delivery</chargesComponent>
            </statementCharge>
        </statementCharges>
    </tariffStatement>
    <tariffStatement>
        <sourceDocKind>Statement</sourceDocKind>
        <sourceURL>https://ets.dps.ny.gov/ets_web/search/showPDF.cfm?G%3E%29S2%3DJ9JSBW%27%5EJK%28%21%5CKK4%3FXVAHQQ%3AW%2FLJ%5B%5E%3AICSBNKB%5FC%2A69NBFZ%0A</sourceURL>
        <datePublished>2024-05-17</datePublished>
        <effectivePeriod>
            <startDate>2024-06-01</startDate>
        </effectivePeriod>
        <iedrOrgAbbreviation>CED</iedrOrgAbbreviation>
        <dpsUtilityPscNumber>10</dpsUtilityPscNumber>
        <serviceType>Electric</serviceType>
        <typeCode>VDER-CR</typeCode>
        <DPSCaseNumber>15-E-0751</DPSCaseNumber>
        <generalRuleRefs>https://ets.dps.ny.gov/ets_web/search/searchSubmissionID.cfm?sub_id=2825845</generalRuleRefs>
        <statementCharges>
            <scopeOfApplicability>
                <include>
                    <serviceClasses>
                        <serviceClass>All</serviceClass>
                    </serviceClasses>
                </include>
                <exclude>
                    <serviceClasses>
                        <serviceClass>11</serviceClass>
                        <serviceClass>12</serviceClass>
                    </serviceClasses>
                </exclude>
            </scopeOfApplicability>
            <statementCharge>
                <servicePeriod>
                    <startDate>2024-06-01</startDate>
                </servicePeriod>
                <chargeName>VDER Cost Recovery</chargeName>
                <description>VDER Cost Recovery</description>
                <chargeValue>0.0038</chargeValue>
                <measurementDefinition>
                    <calculationMethod>by_metered_quantity</calculationMethod>
                    <measurementSource>energy</measurementSource>
                    <unitOfMeasure>Wh</unitOfMeasure>
                    <unitMultiplierPowerOfTen>1</unitMultiplierPowerOfTen>
                    <measurementInterval>
                        <calculationMode>PERIOD</calculationMode>
                        <calcIntervalKind>MONTH</calcIntervalKind>
                        <calcIntervalPer>1</calcIntervalPer>
                    </measurementInterval>
                </measurementDefinition>
                <chargesComponent>delivery</chargesComponent>
            </statementCharge>
        </statementCharges>
    </tariffStatement>
    <tariffStatement>
        <sourceDocKind>Statement</sourceDocKind>
        <sourceURL>https://ets.dps.ny.gov/ets_web/search/showPDF.cfm?G%3E%29S2%3DJ9JSBW%27%5EJO%28%21%3CKK4%3FXVAHQQ%3AW%2FLJ%5B%5E%3AICSBNKB%5FC%2A69NBFZ%0A</sourceURL>
        <datePublished>2024-05-29</datePublished>
        <effectivePeriod>
            <startDate>2024-06-01</startDate>
        </effectivePeriod>
        <iedrOrgAbbreviation>CED</iedrOrgAbbreviation>
        <dpsUtilityPscNumber>10</dpsUtilityPscNumber>
        <serviceType>Electric</serviceType>
        <typeCode>VDER-CRED</typeCode>
        <DPSCaseNumber>nan</DPSCaseNumber>
        <generalRuleRefs>https://ets.dps.ny.gov/ets_web/search/searchSubmissionID.cfm?sub_id=2825983</generalRuleRefs>
        <statementCharges>
            <scopeOfApplicability>
                <include>
                    <serviceClasses>
                        <serviceClass>All</serviceClass>
                    </serviceClasses>
                </include>
                <exclude>
                    <serviceClasses>
                        <serviceClass>11</serviceClass>
                        <serviceClass>12</serviceClass>
                    </serviceClasses>
                </exclude>
            </scopeOfApplicability>
            <statementCharge>
                <servicePeriod>
                    <startDate>2024-06-01</startDate>
                </servicePeriod>
                <chargeName>Value Stack Crediting</chargeName>
                <description>Value Stack Crediting</description>
                <chargeValue>0.18375</chargeValue>
                <measurementDefinition>
                    <calculationMethod>by_metered_quantity</calculationMethod>
                    <measurementSource>energy</measurementSource>
                    <unitOfMeasure>Wh</unitOfMeasure>
                    <unitMultiplierPowerOfTen>1</unitMultiplierPowerOfTen>
                    <measurementInterval>
                        <calculationMode>PERIOD</calculationMode>
                        <calcIntervalKind>MONTH</calcIntervalKind>
                        <calcIntervalPer>1</calcIntervalPer>
                    </measurementInterval>
                </measurementDefinition>
                <chargesComponent>export</chargesComponent>
            </statementCharge>
        </statementCharges>
    </tariffStatement>
</tariffStatements>
